materializecssform/__init__.py
materializecssform/config.py
materializecssform/meta.py
materializecssform/tests.py
materializecssform/templates/materializecssform/attrs.html
materializecssform/templates/materializecssform/field.html
materializecssform/templates/materializecssform/field_icon.html
materializecssform/templates/materializecssform/form.html
materializecssform/templates/materializecssform/formset.html
materializecssform/templatetags/__init__.py
materializecssform/templatetags/materializecss.py
django_materializecss_form-1.1.17.dist-info/LICENSE
django_materializecss_form-1.1.17.dist-info/METADATA
django_materializecss_form-1.1.17.dist-info/WHEEL
django_materializecss_form-1.1.17.dist-info/top_level.txt
django_materializecss_form-1.1.17.dist-info/RECORD
