Metadata-Version: 2.1
Name: django-materializecss-form
Version: 1.1.17
Summary: A simple Django form template tag to work with Materializecss
Home-page: https://github.com/kalwalkden/django-materializecss-form
Author: Kal Walkden, Samuel von Stachelski
Author-email: kal@walkden.us, sam@basx.dev
Maintainer: Kal Walkden, Samuel von Stachelski
Maintainer-email: kal@walkden.us, sam@basx.dev
License: MIT
Keywords: materialize,django,css,materializecss,django forms
Platform: UNKNOWN
Classifier: Development Status :: 5 - Production/Stable
Classifier: Framework :: Django
Classifier: Intended Audience :: Developers
Classifier: Natural Language :: English
Classifier: License :: OSI Approved :: MIT License
Classifier: Operating System :: OS Independent
Classifier: Programming Language :: Python
Classifier: Programming Language :: Python :: 3
Classifier: Programming Language :: Python :: 3.4
Classifier: Programming Language :: Python :: 3.5
Classifier: Programming Language :: Python :: 3.6
Classifier: Programming Language :: Python :: 3.7
Classifier: Programming Language :: Python :: 3.8
Classifier: Programming Language :: Python :: Implementation :: CPython
Classifier: Programming Language :: Python :: Implementation :: PyPy
Classifier: Topic :: Software Development :: Libraries :: Python Modules
